testauto/__init__.py
testauto/__main__.py
testauto/case.py
testauto/core.py
testauto/recorder.py
testauto/runner.py
testauto/task.py
testauto/util.py
testauto_test/__init__.py
testauto_test/case_for_doc.py
testauto_test/case_test.py
testauto_test/core_test.py
testauto_test/recorder_test.py
testauto_test/runner_test.py
testauto_test/task_for_doc.py
testauto_test/task_test.py
testauto_test/until_test.py
test_auto-1.0.2.dist-info/LICENSE
test_auto-1.0.2.dist-info/METADATA
test_auto-1.0.2.dist-info/WHEEL
test_auto-1.0.2.dist-info/top_level.txt
test_auto-1.0.2.dist-info/RECORD
