Metadata-Version: 2.1
Name: test-auto
Version: 1.0.2
Summary: 自动化测试框架，支持多线程和参数化测试，且自带HTML测试报告！
Home-page: https://github.com/lujiatao2
Author: 卢家涛
Author-email: 522430860@qq.com
License: MIT
Project-URL: Source, https://github.com/lujiatao2/testauto
Project-URL: Changelog, https://github.com/lujiatao2/testauto/blob/master/CHANGELOG.md
Platform: UNKNOWN
Classifier: Topic :: Software Development
Classifier: Topic :: Software Development :: Testing
Classifier: Topic :: Software Development :: Testing :: Unit
Classifier: Development Status :: 5 - Production/Stable
Classifier: License :: OSI Approved :: MIT License
Classifier: Programming Language :: Python
Classifier: Programming Language :: Python :: 3
Classifier: Programming Language :: Python :: 3.7
Classifier: Intended Audience :: Developers
Classifier: Natural Language :: Chinese (Simplified)
